changelogs/__init__.py
changelogs/admin.py
changelogs/apps.py
changelogs/models.py
changelogs/tests.py
changelogs/views.py
changelogs/migrations/0001_initial.py
changelogs/migrations/__init__.py
whatsnew/__init__.py
whatsnew/admin.py
whatsnew/apps.py
whatsnew/models.py
whatsnew/tests.py
whatsnew/views.py
whatsnew/migrations/0001_initial.py
whatsnew/migrations/0002_changelog_description.py
whatsnew/migrations/0003_auto_20201206_1546.py
whatsnew/migrations/0004_auto_20201206_1702.py
whatsnew/migrations/0005_auto_20201206_1806.py
whatsnew/migrations/0006_auto_20201206_1814.py
whatsnew/migrations/__init__.py
django_changelogs-0.1.dist-info/METADATA
django_changelogs-0.1.dist-info/WHEEL
django_changelogs-0.1.dist-info/top_level.txt
django_changelogs-0.1.dist-info/RECORD
